Workbook

Sheet plantilla Informe de Gestión
J1: INFORME DE GESTION DE CARTERA RESIDENCIAL, AFIANCOL Y COMERCIALES
J2: PERIODO DE GESTION: COMENTARIOS MARZO 2026
J3: CONTRATISTA: EMDECOB / UNIDAD OPERATIVA: 1572, 4640, 2572, 5452 Y 2081
AI6: Nota: Aquí se debe registrar el nuevo numero de celular que se debe actualizar al titular de la factura en OSF, solo aplica para los nuevos celulares que identifiquemos que el titular cambio. | BS6: GESTIONES VISITA | BT6: MOTIVO DE NO PAGO | BU6: GESTOR DE CAMPO
A7: CARTERA | B7: DEPARTAMENTO | C7: MUNICIPIO | D7: CONTRATO | E7: PRODUCTO | F7: TIPO PRODUCTO | G7: OT | H7: SINCRONIZACION | I7: FRANJA | J7: FECHA DE ASIGNACION | K7: REINCIDENCIA | L7: ASIGNADO | M7: REVISION PERIODICA | N7: CEDULA | O7: TELEFONO | P7: NOMBRE | Q7: TELEFONO HISTORIAL | R7: NOMBRE DEUDOR | S7: CEDULA DEUDOR | T7: TELEFONO DEUDOR | U7: NOMBRE CODEUDOR | V7: CEDULA CODEUDOR | W7: TELEFONO CODEUDOR | X7: ULTIMO TELEFONO IDENTIFICADO | Y7: HISTORIAL TELEFONO IDENTIFICADO | Z7: CORREO IDENTIFICADO | AA7: ULTIMO TELEFONO CONTACTO | AB7: CATEGORIA | AC7: ESTRATO | AD7: EDAD MORA | AE7: DIAS MORA | AF7: DEUDA CORRIENTE NO VENCIDA | AG7: DEUDA CORRIENTE VENCIDA | AH7: TOTAL DEUDA CORRIENTE | AI7: DEUDA NO CORRIENTE | AJ7: DEUDA TOTAL | AK7: ESTADO PRODUCTO | AL7: ESTADO FINANCIERO | AM7: BARRIO | AN7: DIRECCION | AO7: RUTA | AP7: CONSECUTIVO | AQ7: CICLO | AR7: DESCRIPCION CICLO | AS7: LIQUIDACION | AT7: VENCIMIENTOS | AU7: ESTADO DE CORTE | AV7: NO. FACTURAS VENCIDAS | AW7: MEDIDOR | AX7: ULTIMA ACTIVIDAD SUSPENSION | AY7: REINCIDENCIA HISTORICA | AZ7: EDADMORAASIGNACION | BA7: EDADMORAAGRUPADAASIGNACION | BB7: FIANZA | BC7: DESINCRONIZADO | BD7: SCORING | BE7: SALDOMENOR | BF7: SEGMENTO | BG7: IDUNIDADOPERATIVA | BH7: NOMBREUNIDADOPERATIVA | BI7: CREDITO AFIANZADO | BJ7: RUTA2 | BK7: PAGO | BL7: FECHA | BM7: CONV BASE | BN7: DESCRIPCION COMENTARIO | BO7: CONV MOTIVO DE NO PAGO | BP7: DESCRIPCION CAUSAL | BQ7: CODIGO CAUSAL | BR7: OBSERVACIONES GESTION DEL MES | BS7: VISITAS DESCRIPCION COMENTARIO | BT7: VISITAS DESCRIPCION CAUSAL | BU7: VISITAS OBSERVACIONES GESTION DEL MES

Sheet COMENTARIOS MASIVO
A1: ESTAS COLUMNAS YA VIENEN VINCULADAS DE LA HOJA ASIGNACION - FAVOR NO MODIFICAR RECUERDEN ARRASTRAR LA FORMULA PARA QUE QUEDEN COMPLETOS LOS COMENTARIOS.
A2: Numero orden | B2: Codigo Comentario | C2: Observacion | D2: TEXTO PARA PEGAR EN EL ARCHIVO PLANO
A3: =+'plantilla Informe de Gestión'!#REF! -> #REF! | B3: =+'plantilla Informe de Gestión'!#REF! -> #REF! | C3: =+'plantilla Informe de Gestión'!#REF! -> #REF! | D3: =CONCATENATE(A3,"|",B3,"|",C3) -> #REF!
A4: =+'plantilla Informe de Gestión'!#REF! -> #REF! | B4: =+'plantilla Informe de Gestión'!#REF! -> #REF! | C4: =+'plantilla Informe de Gestión'!#REF! -> #REF! | D4: =CONCATENATE(A4,"|",B4,"|",C4) -> #REF!
A5: =+'plantilla Informe de Gestión'!#REF! -> #REF! | B5: =+'plantilla Informe de Gestión'!#REF! -> #REF! | C5: =+'plantilla Informe de Gestión'!#REF! -> #REF! | D5: =CONCATENATE(A5,"|",B5,"|",C5) -> #REF!
A6: =+'plantilla Informe de Gestión'!#REF! -> #REF! | B6: =+'plantilla Informe de Gestión'!#REF! -> #REF! | C6: =+'plantilla Informe de Gestión'!#REF! -> #REF! | D6: =CONCATENATE(A6,"|",B6,"|",C6) -> #REF!
A7: =+'plantilla Informe de Gestión'!#REF! -> #REF! | B7: =+'plantilla Informe de Gestión'!#REF! -> #REF! | C7: =+'plantilla Informe de Gestión'!#REF! -> #REF! | D7: =CONCATENATE(A7,"|",B7,"|",C7) -> #REF!
A8: =+'plantilla Informe de Gestión'!#REF! -> #REF! | B8: =+'plantilla Informe de Gestión'!#REF! -> #REF! | C8: =+'plantilla Informe de Gestión'!#REF! -> #REF! | D8: =CONCATENATE(A8,"|",B8,"|",C8) -> #REF!
A9: =+'plantilla Informe de Gestión'!#REF! -> #REF! | B9: =+'plantilla Informe de Gestión'!#REF! -> #REF! | C9: =+'plantilla Informe de Gestión'!#REF! -> #REF! | D9: =CONCATENATE(A9,"|",B9,"|",C9) -> #REF!
A10: =+'plantilla Informe de Gestión'!#REF! -> #REF! | B10: =+'plantilla Informe de Gestión'!#REF! -> #REF! | C10: =+'plantilla Informe de Gestión'!#REF! -> #REF! | D10: =CONCATENATE(A10,"|",B10,"|",C10) -> #REF!
A11: =+'plantilla Informe de Gestión'!#REF! -> #REF! | B11: =+'plantilla Informe de Gestión'!#REF! -> #REF! | C11: =+'plantilla Informe de Gestión'!#REF! -> #REF! | D11: =CONCATENATE(A11,"|",B11,"|",C11) -> #REF!
A12: =+'plantilla Informe de Gestión'!#REF! -> #REF! | B12: =+'plantilla Informe de Gestión'!#REF! -> #REF! | C12: =+'plantilla Informe de Gestión'!#REF! -> #REF! | D12: =CONCATENATE(A12,"|",B12,"|",C12) -> #REF!
A13: =+'plantilla Informe de Gestión'!#REF! -> #REF! | B13: =+'plantilla Informe de Gestión'!#REF! -> #REF! | C13: =+'plantilla Informe de Gestión'!#REF! -> #REF! | D13: =CONCATENATE(A13,"|",B13,"|",C13) -> #REF!
A14: =+'plantilla Informe de Gestión'!#REF! -> #REF! | B14: =+'plantilla Informe de Gestión'!#REF! -> #REF! | C14: =+'plantilla Informe de Gestión'!#REF! -> #REF! | D14: =CONCATENATE(A14,"|",B14,"|",C14) -> #REF!
... A2948: =+'plantilla Informe de Gestión'!#REF! -> #REF! | B2948: =+'plantilla Informe de Gestión'!#REF! -> #REF! | C2948: =+'plantilla Informe de Gestión'!#REF! -> #REF! | D2948: =CONCATENATE(A2948,"|",B2948,"|",C2948) -> #REF!
A2949: =+'plantilla Informe de Gestión'!G8 -> 0 | B2949: =+'plantilla Informe de Gestión'!BO8 -> 0 | C2949: =+'plantilla Informe de Gestión'!BR8 -> 0 | D2949: =CONCATENATE(A2949,"|",B2949,"|",C2949) -> 0|0|0
A2950: =+'plantilla Informe de Gestión'!G9 -> 0 | B2950: =+'plantilla Informe de Gestión'!BO9 -> 0 | C2950: =+'plantilla Informe de Gestión'!BR9 -> 0 | D2950: =CONCATENATE(A2950,"|",B2950,"|",C2950) -> 0|0|0
A2951: =+'plantilla Informe de Gestión'!G10 -> 0 | B2951: =+'plantilla Informe de Gestión'!BO10 -> 0 | C2951: =+'plantilla Informe de Gestión'!BR10 -> 0 | D2951: =CONCATENATE(A2951,"|",B2951,"|",C2951) -> 0|0|0
A2952: =+'plantilla Informe de Gestión'!G11 -> 0 | B2952: =+'plantilla Informe de Gestión'!BO11 -> 0 | C2952: =+'plantilla Informe de Gestión'!BR11 -> 0 | D2952: =CONCATENATE(A2952,"|",B2952,"|",C2952) -> 0|0|0
A2953: =+'plantilla Informe de Gestión'!G12 -> 0 | B2953: =+'plantilla Informe de Gestión'!BO12 -> 0 | C2953: =+'plantilla Informe de Gestión'!BR12 -> 0 | D2953: =CONCATENATE(A2953,"|",B2953,"|",C2953) -> 0|0|0
A2954: =+'plantilla Informe de Gestión'!G13 -> 0 | B2954: =+'plantilla Informe de Gestión'!BO13 -> 0 | C2954: =+'plantilla Informe de Gestión'!BR13 -> 0 | D2954: =CONCATENATE(A2954,"|",B2954,"|",C2954) -> 0|0|0
A2955: =+'plantilla Informe de Gestión'!G14 -> 0 | B2955: =+'plantilla Informe de Gestión'!BO14 -> 0 | C2955: =+'plantilla Informe de Gestión'!BR14 -> 0 | D2955: =CONCATENATE(A2955,"|",B2955,"|",C2955) -> 0|0|0
A2956: =+'plantilla Informe de Gestión'!G15 -> 0 | B2956: =+'plantilla Informe de Gestión'!BO15 -> 0 | C2956: =+'plantilla Informe de Gestión'!BR15 -> 0 | D2956: =CONCATENATE(A2956,"|",B2956,"|",C2956) -> 0|0|0
A2957: =+'plantilla Informe de Gestión'!G16 -> 0 | B2957: =+'plantilla Informe de Gestión'!BO16 -> 0 | C2957: =+'plantilla Informe de Gestión'!BR16 -> 0 | D2957: =CONCATENATE(A2957,"|",B2957,"|",C2957) -> 0|0|0
A2958: =+'plantilla Informe de Gestión'!G17 -> 0 | B2958: =+'plantilla Informe de Gestión'!BO17 -> 0 | C2958: =+'plantilla Informe de Gestión'!BR17 -> 0 | D2958: =CONCATENATE(A2958,"|",B2958,"|",C2958) -> 0|0|0
A2959: =+'plantilla Informe de Gestión'!G18 -> 0 | B2959: =+'plantilla Informe de Gestión'!BO18 -> 0 | C2959: =+'plantilla Informe de Gestión'!BR18 -> 0 | D2959: =CONCATENATE(A2959,"|",B2959,"|",C2959) -> 0|0|0
A2960: =+'plantilla Informe de Gestión'!G19 -> 0 | B2960: =+'plantilla Informe de Gestión'!BO19 -> 0 | C2960: =+'plantilla Informe de Gestión'!BR19 -> 0 | D2960: =CONCATENATE(A2960,"|",B2960,"|",C2960) -> 0|0|0
... A3439: =+'plantilla Informe de Gestión'!G498 -> 0 | B3439: =+'plantilla Informe de Gestión'!BO498 -> 0 | C3439: =+'plantilla Informe de Gestión'!BR498 -> 0 | D3439: =CONCATENATE(A3439,"|",B3439,"|",C3439) -> 0|0|0

Sheet CAUSALES RESIDENCIAL
A2: CARTERA | B2: EFIGAS RESIDENCIAL
A3: FRANJA | B3: ESTRATEGICA
C5: Etiquetas de columna
F6: Servicios Financieros | I6: Total TOTAL | J6: Total PESO % | K6: Total # PRODUCTOS
A7: Etiquetas de fila | B7: Motivo no pago | C7: TOTAL | D7: PESO % | E7: # PRODUCTOS | F7: TOTAL | G7: PESO % | H7: # PRODUCTOS
A8: Cliente Con Intencion De Pago 3810 | B8: Acuerdo Incumplido 8956 | C8: 873289 | D8: 0.0023936332 | E8: 4 | F8: 22407323 | G8: 0.010863277 | H8: 4 | I8: 23280612 | J8: 0.0095903442 | K8: 8
B9: Posible Acuerdo 8993 | C9: 17943536 | D9: 0.049182164 | E9: 26 | F9: 123025413 | G9: 0.059643853 | H9: 28 | I9: 140968949 | J9: 0.058071529 | K9: 54
A10: Total Cliente Con Intencion De Pago 3810 | C10: 18816825 | D10: 0.051575797 | E10: 30 | F10: 145432736 | G10: 0.07050713 | H10: 32 | I10: 164249561 | J10: 0.067661874 | K10: 62
A11: Cliente Ilocalizado 3607 | B11: No Contesta - Numero Activo 1474 | C11: 158933116 | D11: 0.43562621 | E11: 372 | F11: 815167883 | G11: 0.3952009 | H11: 153 | I11: 974100999 | J11: 0.40127656 | K11: 525
B12: No Contesta- Numero Equivocado 1473 | C12: 19053906 | D12: 0.052225622 | E12: 20 | F12: 64145864 | G12: 0.031098506 | H12: 14 | I12: 83199770 | J12: 0.034273774 | K12: 34
B13: Deudor No Reside 8982 | C13: 4792978 | D13: 0.013137267 | E13: 5 | F13: 64196627 | G13: 0.031123116 | H13: 12 | I13: 68989605 | J13: 0.02841996 | K13: 17
B14: Predio Desocupado 1384 | C14: 15549203 | D14: 0.04261944 | E14: 15 | F14: 48370916 | G14: 0.023450666 | H14: 8 | I14: 63920119 | J14: 0.026331608 | K14: 23
B15: Nadie En El Predio 9136 | C15: 26019724 | D15: 0.071318515 | E15: 44 | F15: 195786962 | G15: 0.094919322 | H15: 32 | I15: 221806686 | J15: 0.091372274 | K15: 76
B16: Se Deja Informacion Con Un Tercero 9138 | C16: 2333499 | D16: 0.0063959819 | E16: 3 | F16: 3142524 | G16: 0.0015235246 | H16: 2 | I16: 5476023 | J16: 0.0022558232 | K16: 5
A17: Total Cliente Ilocalizado 3607 | C17: 226682426 | D17: 0.62132304 | E17: 459 | F17: 1190810776 | G17: 0.57731603 | H17: 221 | I17: 1417493202 | J17: 0.58393 | K17: 680
A18: Cliente Ilocalizado 3608 | B18: No Contesta- Numero Equivocado 1474 | D18: 0 | F18: 3131937 | G18: 0.0015183919 | H18: 1 | I18: 3131937 | J18: 0.0012901875 | K18: 1
A19: Total Cliente Ilocalizado 3608 | D19: 0 | F19: 3131937 | G19: 0.0015183919 | H19: 1 | I19: 3131937 | J19: 0.0012901875 | K19: 1
A20: Cliente No Asume Deuda 3811 | B20: No Le Interesa Pagar 8991 | C20: 16111319 | D20: 0.044160166 | E20: 15 | F20: 82107858 | G20: 0.039806646 | H20: 16 | I20: 98219177 | J20: 0.040460952 | K20: 31
B21: USUARIO FALLECIDO 1345 | D21: 0 | F21: 12826371 | G21: 0.0062183428 | H21: 5 | I21: 12826371 | J21: 0.0052837663 | K21: 5
B22: Desacuerdo Con El Cobro (Reclamacion,Rtr, Instalaicon,Certificacion) 1474 | D22: 0 | F22: 122571 | G22: 5.942355e-05 | H22: 1 | I22: 122571 | J22: 5.0492576e-05 | K22: 1
A23: Total Cliente No Asume Deuda 3811 | C23: 16111319 | D23: 0.044160166 | E23: 15 | F23: 95056800 | G23: 0.046084412 | H23: 22 | I23: 111168119 | J23: 0.045795211 | K23: 37
A24: Cliente Realiza Abono 1367 | B24: Cliente Realiza Abono 1367 | C24: 20398947 | D24: 0.055912299 | E24: 13 | F24: 124303217 | G24: 0.060263344 | H24: 21 | I24: 144702164 | J24: 0.059609411 | K24: 34
A25: Total Cliente Realiza Abono 1367 | C25: 20398947 | D25: 0.055912299 | E25: 13 | F25: 124303217 | G25: 0.060263344 | H25: 21 | I25: 144702164 | J25: 0.059609411 | K25: 34
A26: Cliente Realiza Pago Total 1368 | B26: Cliente Realiza Pago Total 1368 | C26: 8869292 | D26: 0.024310201 | E26: 42 | F26: 24211301 | G26: 0.011737862 | H26: 9 | I26: 33080593 | J26: 0.013627403 | K26: 51
A27: Total Cliente Realiza Pago Total 1368 | C27: 8869292 | D27: 0.024310201 | E27: 42 | F27: 24211301 | G27: 0.011737862 | H27: 9 | I27: 33080593 | J27: 0.013627403 | K27: 51
A28: Cliente Realiza Refinanciacion 1369 | B28: Cliente Realiza Refinanciacion 1369 | C28: 13555610 | D28: 0.03715512 | E28: 12 | F28: 120805346 | G28: 0.058567544 | H28: 29 | I28: 134360956 | J28: 0.055349396 | K28: 41
A29: Total Cliente Realiza Refinanciacion 1369 | C29: 13555610 | D29: 0.03715512 | E29: 12 | F29: 120805346 | G29: 0.058567544 | H29: 29 | I29: 134360956 | J29: 0.055349396 | K29: 41
A30: Contacto Indirecto-Gestion Telefonica 3812 | B30: Se Deja Informacion Con Un Tercero 8961 | C30: 22252363 | D30: 0.060992402 | E30: 27 | F30: 135528532 | G30: 0.065705481 | H30: 30 | I30: 157780895 | J30: 0.064997136 | K30: 57
B31: Se Deja Informacion Con Un Tercero 9138 | C31: 438695 | D31: 0.0012024369 | E31: 1 | G31: 0 | I31: 438695 | J31: 0.00018071845 | K31: 1
A32: Total Contacto Indirecto-Gestion Telefonica 3812 | C32: 22691058 | D32: 0.062194839 | E32: 28 | F32: 135528532 | G32: 0.065705481 | H32: 30 | I32: 158219590 | J32: 0.065177854 | K32: 58
A33: Mala Situacion Economica 3741 | B33: Sin Capacidad De Pago 8998 | C33: 2335435 | D33: 0.0064012883 | E33: 6 | F33: 13805621 | G33: 0.0066930922 | H33: 3 | I33: 16141056 | J33: 0.006649236 | K33: 9
B34: Cliente Desempleado 8977 | C34: 6731843 | D34: 0.018451581 | E34: 6 | F34: 34744311 | G34: 0.016844362 | H34: 6 | I34: 41476154 | J34: 0.017085917 | K34: 12
B35: Enfermedad Y/O Calamidad 9125 | C35: 723996 | D35: 0.0019844299 | E35: 2 | F35: 12884271 | G35: 0.0062464132 | H35: 2 | I35: 13608267 | J35: 0.0056058649 | K35: 4
A36: Total Mala Situacion Economica 3741 | C36: 9791274 | D36: 0.026837299 | E36: 14 | F36: 61434203 | G36: 0.029783867 | H36: 11 | I36: 71225477 | J36: 0.029341017 | K36: 25
A37: Promesa De Pago 3814 | B37: Promesa De Pago 1315 | C37: 27921526 | D37: 0.076531241 | E37: 36 | F37: 155536525 | G37: 0.07540554 | H37: 36 | I37: 183458051 | J37: 0.075574725 | K37: 72
B38: Negociacion En Campo 1478 | D38: 0 | F38: 6415711 | G38: 0.0031103958 | H38: 1 | I38: 6415711 | J38: 0.0026429235 | K38: 1
A39: Total Promesa De Pago 3814 | C39: 27921526 | D39: 0.076531241 | E39: 36 | F39: 161952236 | G39: 0.078515936 | H39: 37 | I39: 189873762 | J39: 0.078217649 | K39: 73
A40: Total general | C40: 364838277 | D40: 1 | E40: 649 | F40: 2062667084 | G40: 1 | H40: 413 | I40: 2427505361 | J40: 1 | K40: 1062

Sheet CAUSALES AFIANCOL
A2: CARTERA | B2: EFIGAS AFIANZADO
A3: FRANJA | B3: ESTRATEGICA
C5: Etiquetas de columna
C6: Servicios Financieros | F6: Total TOTAL | G6: Total # PRODUCTOS | H6: Total PESO %
A7: Etiquetas de fila | B7: Motivo no pago | C7: TOTAL | D7: # PRODUCTOS | E7: PESO %
A8: Cliente Con Intencion De Pago 3810 | B8: Posible Acuerdo 8993 | C8: 35131008 | D8: 7 | E8: 0.0136091 | F8: 35131008 | G8: 7 | H8: 0.0136091
A9: Total Cliente Con Intencion De Pago 3810 | C9: 35131008 | D9: 7 | E9: 0.0136091 | F9: 35131008 | G9: 7 | H9: 0.0136091
A10: Cliente Ilocalizado 3607 | B10: Deudor No Reside 8982 | C10: 873062375 | D10: 173 | E10: 0.33820814 | F10: 873062375 | G10: 173 | H10: 0.33820814
B11: Nadie En El Predio 9136 | C11: 765547089 | D11: 153 | E11: 0.29655872 | F11: 765547089 | G11: 153 | H11: 0.29655872
B12: No Contesta - Numero Activo 1474 | C12: 326645271 | D12: 92 | E12: 0.12653631 | F12: 326645271 | G12: 92 | H12: 0.12653631
B13: No Contesta- Numero Equivocado 1473 | C13: 61807222 | D13: 16 | E13: 0.023942969 | F13: 61807222 | G13: 16 | H13: 0.023942969
B14: Predio Abandonado 1382 | C14: 2969544 | D14: 1 | E14: 0.0011503462 | F14: 2969544 | G14: 1 | H14: 0.0011503462
B15: Predio Desocupado 1384 | C15: 143184927 | D15: 26 | E15: 0.05546718 | F15: 143184927 | G15: 26 | H15: 0.05546718
B16: Se Deja Informacion Con Un Tercero 9138 | C16: 38497341 | D16: 8 | E16: 0.014913155 | F16: 38497341 | G16: 8 | H16: 0.014913155
A17: Total Cliente Ilocalizado 3607 | C17: 2211713769 | D17: 469 | E17: 0.85677682 | F17: 2211713769 | G17: 469 | H17: 0.85677682
A18: Cliente No Asume Deuda 3811 | B18: No Le Interesa Pagar 8991 | C18: 81519105 | D18: 17 | E18: 0.031578987 | F18: 81519105 | G18: 17 | H18: 0.031578987
B19: Posible Fraude 1475 | C19: 6519722 | D19: 1 | E19: 0.0025256192 | F19: 6519722 | G19: 1 | H19: 0.0025256192
B20: USUARIO FALLECIDO 1345 | C20: 14597002 | D20: 2 | E20: 0.0056546074 | F20: 14597002 | G20: 2 | H20: 0.0056546074
B21: Usuario No Asume Solidaridad (No Autorizo, No Es Titular) 8959 | C21: 7083688 | D21: 2 | E21: 0.0027440891 | F21: 7083688 | G21: 2 | H21: 0.0027440891
A22: Total Cliente No Asume Deuda 3811 | C22: 109719517 | D22: 22 | E22: 0.042503302 | F22: 109719517 | G22: 22 | H22: 0.042503302
A23: Cliente Realiza Abono 1367 | B23: Cliente Realiza Abono 1367 | C23: 6342125 | D23: 2 | E23: 0.0024568214 | F23: 6342125 | G23: 2 | H23: 0.0024568214
A24: Total Cliente Realiza Abono 1367 | C24: 6342125 | D24: 2 | E24: 0.0024568214 | F24: 6342125 | G24: 2 | H24: 0.0024568214
A25: Cliente Realiza Pago Total 1368 | B25: Cliente Realiza Pago Total 1368 | C25: 814539 | D25: 1 | E25: 0.00031553728 | F25: 814539 | G25: 1 | H25: 0.00031553728
A26: Total Cliente Realiza Pago Total 1368 | C26: 814539 | D26: 1 | E26: 0.00031553728 | F26: 814539 | G26: 1 | H26: 0.00031553728
A27: Cliente Realiza Refinanciacion 1369 | B27: Cliente Realiza Refinanciacion 1369 | C27: 13376910 | D27: 3 | E27: 0.0051819664 | F27: 13376910 | G27: 3 | H27: 0.0051819664
A28: Total Cliente Realiza Refinanciacion 1369 | C28: 13376910 | D28: 3 | E28: 0.0051819664 | F28: 13376910 | G28: 3 | H28: 0.0051819664
A29: Contacto Indirecto-Gestion Telefonica 3812 | B29: Se Deja Informacion Con Un Tercero 8961 | C29: 155442080 | D29: 26 | E29: 0.060215374 | F29: 155442080 | G29: 26 | H29: 0.060215374
B30: Se Deja Informacion Con Un Tercero 9138 | C30: 8082424 | D30: 1 | E30: 0.0031309809 | F30: 8082424 | G30: 1 | H30: 0.0031309809
A31: Total Contacto Indirecto-Gestion Telefonica 3812 | C31: 163524504 | D31: 27 | E31: 0.063346355 | F31: 163524504 | G31: 27 | H31: 0.063346355
A32: Mala Situacion Economica 3741 | B32: Cliente Desempleado 8977 | C32: 3211115 | D32: 1 | E32: 0.0012439263 | F32: 3211115 | G32: 1 | H32: 0.0012439263
B33: Sin Capacidad De Pago 8998 | C33: 6805937 | D33: 1 | E33: 0.0026364935 | F33: 6805937 | G33: 1 | H33: 0.0026364935
A34: Total Mala Situacion Economica 3741 | C34: 10017052 | D34: 2 | E34: 0.0038804198 | F34: 10017052 | G34: 2 | H34: 0.0038804198
A35: Problemas Juridicos 3813 | B35: Cliente En Proceso Juridico 1477 | C35: 4036607 | D35: 2 | E35: 0.0015637066 | F35: 4036607 | G35: 2 | H35: 0.0015637066
A36: Total Problemas Juridicos 3813 | C36: 4036607 | D36: 2 | E36: 0.0015637066 | F36: 4036607 | G36: 2 | H36: 0.0015637066
A37: Promesa De Pago 3814 | B37: Promesa De Pago 1315 | C37: 26759077 | D37: 5 | E37: 0.010365969 | F37: 26759077 | G37: 5 | H37: 0.010365969
A38: Total Promesa De Pago 3814 | C38: 26759077 | D38: 5 | E38: 0.010365969 | F38: 26759077 | G38: 5 | H38: 0.010365969
A39: Total general | C39: 2581435108 | D39: 540 | E39: 1 | F39: 2581435108 | G39: 540 | H39: 1

Sheet CAUSALES COMERCIALES
A2: CARTERA | B2: EFIGAS COMERCIALES
A3: FRANJA | B3: ESTRATEGICA
C5: Etiquetas de columna
C6: Gas | F6: Total TOTAL | G6: Total # PRODUCTOS | H6: Total PESO %
A7: Etiquetas de fila | B7: Motivo no pago | C7: TOTAL | D7: # PRODUCTOS | E7: PESO %
A8: Cliente Ilocalizado 3607 | B8: Deudor No Reside 8982 | C8: 126915 | D8: 2 | E8: 0.0025668734 | F8: 126915 | G8: 2 | H8: 0.0025668734
B9: No Contesta - Numero Activo 1474 | C9: 13321531 | D9: 87 | E9: 0.2694298 | F9: 13321531 | G9: 87 | H9: 0.2694298
B10: No Contesta- Numero Equivocado 1473 | C10: 1258467 | D10: 20 | E10: 0.025452669 | F10: 1258467 | G10: 20 | H10: 0.025452669
B11: Predio Desocupado 1384 | C11: 5749906 | D11: 1 | E11: 0.11629264 | F11: 5749906 | G11: 1 | H11: 0.11629264
A12: Total Cliente Ilocalizado 3607 | C12: 20456819 | D12: 110 | E12: 0.41374199 | F12: 20456819 | G12: 110 | H12: 0.41374199
A13: Cliente No Asume Deuda 3811 | B13: Desacuerdo Con El Cobro (Reclamacion,Rtr, Instalaicon,Certificacion) 1474 | C13: 52642 | D13: 1 | E13: 0.0010646917 | F13: 52642 | G13: 1 | H13: 0.0010646917
B14: No Le Interesa Pagar 8991 | C14: 11490218 | D14: 4 | E14: 0.23239125 | F14: 11490218 | G14: 4 | H14: 0.23239125
A15: Total Cliente No Asume Deuda 3811 | C15: 11542860 | D15: 5 | E15: 0.23345594 | F15: 11542860 | G15: 5 | H15: 0.23345594
A16: Cliente Realiza Pago Total 1368 | B16: Cliente Realiza Pago Total 1368 | C16: 11007428 | D16: 10 | E16: 0.22262675 | F16: 11007428 | G16: 10 | H16: 0.22262675
A17: Total Cliente Realiza Pago Total 1368 | C17: 11007428 | D17: 10 | E17: 0.22262675 | F17: 11007428 | G17: 10 | H17: 0.22262675
A18: Cliente Realiza Refinanciacion 1369 | B18: Cliente Realiza Refinanciacion 1369 | C18: 1609802 | D18: 1 | E18: 0.032558468 | F18: 1609802 | G18: 1 | H18: 0.032558468
A19: Total Cliente Realiza Refinanciacion 1369 | C19: 1609802 | D19: 1 | E19: 0.032558468 | F19: 1609802 | G19: 1 | H19: 0.032558468
A20: Contacto Indirecto-Gestion Telefonica 3812 | B20: Se Deja Informacion Con Un Tercero 8961 | C20: 4346697 | D20: 5 | E20: 0.087912547 | F20: 4346697 | G20: 5 | H20: 0.087912547
A21: Total Contacto Indirecto-Gestion Telefonica 3812 | C21: 4346697 | D21: 5 | E21: 0.087912547 | F21: 4346697 | G21: 5 | H21: 0.087912547
A22: Promesa De Pago 3814 | B22: Promesa De Pago 1315 | C22: 479814 | D22: 2 | E22: 0.0097043044 | F22: 479814 | G22: 2 | H22: 0.0097043044
A23: Total Promesa De Pago 3814 | C23: 479814 | D23: 2 | E23: 0.0097043044 | F23: 479814 | G23: 2 | H23: 0.0097043044
A24: Total general | C24: 49443420 | D24: 133 | E24: 1 | F24: 49443420 | G24: 133 | H24: 1

Sheet CAUSALES RISARALDA
A2: CARTERA | B2: EFIGAS AFIANZADO RISARALDA
A3: FRANJA | B3: ESTRATEGICA
C5: Etiquetas de columna
C6: Servicios Financieros | F6: Total TOTAL | G6: Total # PRODUCTOS | H6: Total PESO %
A7: Etiquetas de fila | B7: Motivo no pago | C7: TOTAL | D7: # PRODUCTOS | E7: PESO %
A8: Cliente Con Intencion De Pago 3810 | B8: Posible Acuerdo 8993 | C8: 15823798 | D8: 3 | E8: 0.005156811 | F8: 15823798 | G8: 3 | H8: 0.005156811
A9: Total Cliente Con Intencion De Pago 3810 | C9: 15823798 | D9: 3 | E9: 0.005156811 | F9: 15823798 | G9: 3 | H9: 0.005156811
A10: Cliente Ilocalizado 3607 | B10: No Contesta - Numero Activo 1474 | C10: 1238079829 | D10: 253 | E10: 0.40347733 | F10: 1238079829 | G10: 253 | H10: 0.40347733
B11: No Contesta- Numero Equivocado 1473 | C11: 1793420579 | D11: 354 | E11: 0.5844571 | F11: 1793420579 | G11: 354 | H11: 0.5844571
A12: Total Cliente Ilocalizado 3607 | C12: 3031500408 | D12: 607 | E12: 0.98793442 | F12: 3031500408 | G12: 607 | H12: 0.98793442
A13: Cliente No Asume Deuda 3811 | B13: No Le Interesa Pagar 8991 | C13: 11657320 | D13: 3 | E13: 0.0037989992 | F13: 11657320 | G13: 3 | H13: 0.0037989992
B14: USUARIO FALLECIDO 1345 | C14: 9542396 | D14: 1 | E14: 0.0031097675 | F14: 9542396 | G14: 1 | H14: 0.0031097675
A15: Total Cliente No Asume Deuda 3811 | C15: 21199716 | D15: 4 | E15: 0.0069087667 | F15: 21199716 | G15: 4 | H15: 0.0069087667
A16: Total general | C16: 3068523922 | D16: 614 | E16: 1 | F16: 3068523922 | G16: 614 | H16: 1

Sheet CAUSALES PILOTO
A2: CARTERA | B2: EFIGAS PILOTO
A3: FRANJA | B3: (Todas)
C5: Etiquetas de columna
C6: Servicios Financieros | F6: Total TOTAL | G6: Total # PRODUCTOS | H6: Total PESO %
A7: Etiquetas de fila | B7: Motivo no pago | C7: TOTAL | D7: # PRODUCTOS | E7: PESO %
A8: Cliente Con Intencion De Pago 3810 | B8: Posible Acuerdo 8993 | C8: 6632829 | D8: 1 | E8: 0.074338743 | F8: 6632829 | G8: 1 | H8: 0.074338743
A9: Total Cliente Con Intencion De Pago 3810 | C9: 6632829 | D9: 1 | E9: 0.074338743 | F9: 6632829 | G9: 1 | H9: 0.074338743
A10: Cliente Ilocalizado 3607 | B10: No Contesta - Numero Activo 1474 | C10: 69220728 | D10: 12 | E10: 0.775805 | F10: 69220728 | G10: 12 | H10: 0.775805
B11: No Contesta- Numero Equivocado 1473 | C11: 2170507 | D11: 1 | E11: 0.024326387 | F11: 2170507 | G11: 1 | H11: 0.024326387
A12: Total Cliente Ilocalizado 3607 | C12: 71391235 | D12: 13 | E12: 0.80013139 | F12: 71391235 | G12: 13 | H12: 0.80013139
A13: Promesa De Pago 3814 | B13: Promesa De Pago 1315 | C13: 11200326 | D13: 2 | E13: 0.12552987 | F13: 11200326 | G13: 2 | H13: 0.12552987
A14: Total Promesa De Pago 3814 | C14: 11200326 | D14: 2 | E14: 0.12552987 | F14: 11200326 | G14: 2 | H14: 0.12552987
A15: Total general | C15: 89224390 | D15: 16 | E15: 1 | F15: 89224390 | G15: 16 | H15: 1
